specify_extend.py
specify_extend-1.5.7.dist-info/METADATA
specify_extend-1.5.7.dist-info/WHEEL
specify_extend-1.5.7.dist-info/entry_points.txt
specify_extend-1.5.7.dist-info/licenses/LICENSE
specify_extend-1.5.7.dist-info/RECORD
