Metadata-Version: 2.4
Name: specify-extend
Version: 1.5.7
Summary: Installation tool for spec-kit-extensions that works alongside specify init
Project-URL: Homepage, https://github.com/pradeepmouli/spec-kit-extensions
Project-URL: Repository, https://github.com/pradeepmouli/spec-kit-extensions
Project-URL: Issues, https://github.com/pradeepmouli/spec-kit-extensions/issues
License: MIT
License-File: LICENSE
Requires-Python: >=3.11
Requires-Dist: httpx
Requires-Dist: rich
Requires-Dist: typer
